nginxfmt.py
nginxfmt-1.3.0.dist-info/LICENSE
nginxfmt-1.3.0.dist-info/METADATA
nginxfmt-1.3.0.dist-info/WHEEL
nginxfmt-1.3.0.dist-info/entry_points.txt
nginxfmt-1.3.0.dist-info/RECORD
