Metadata-Version: 2.3
Name: nginxfmt
Version: 1.3.0
Summary: nginx config file formatter/beautifier with no additional dependencies.
License: Apache-2.0
Keywords: nginx,formatter,formatting,beautifier
Author: Michał Słomkowski
Author-email: michal@slomkowski.eu
Requires-Python: >=3.4
Classifier: License :: OSI Approved :: Apache Software License
Classifier: Programming Language :: Python :: 3
Classifier: Programming Language :: Python :: 3.4
Classifier: Programming Language :: Python :: 3.5
Classifier: Programming Language :: Python :: 3.6
Classifier: Programming Language :: Python :: 3.7
Classifier: Programming Language :: Python :: 3.8
Classifier: Programming Language :: Python :: 3.9
Classifier: Programming Language :: Python :: 3.10
Classifier: Programming Language :: Python :: 3.11
Classifier: Programming Language :: Python :: 3.12
Classifier: Programming Language :: Python :: 3.13
Project-URL: Homepage, https://github.com/slomkowski/nginx-config-formatter
Project-URL: Repository, https://github.com/slomkowski/nginx-config-formatter
